simur_sample/__init__.py
simur_sample/skeleton.py
simur_sample/core/__init__.py
simur_sample/core/_versions.py
uniovi_simur_sample-8.0.0.dist-info/licenses/LICENSE.txt
uniovi_simur_sample-8.0.0.dist-info/METADATA
uniovi_simur_sample-8.0.0.dist-info/WHEEL
uniovi_simur_sample-8.0.0.dist-info/top_level.txt
uniovi_simur_sample-8.0.0.dist-info/RECORD
