Metadata-Version: 2.4
Name: uniovi-simur-sample
Version: 8.0.0
Summary: Uiovi Simur Sample
Home-page: https://github.com/pyscaffold/pyscaffold/
Author: Miguel Salinas Gancedo
Author-email: masalinas.gancedo@gmail.com
License: MIT
Project-URL: Documentation, https://pyscaffold.org/
Platform: any
Classifier: Development Status :: 4 - Beta
Classifier: Programming Language :: Python
License-File: LICENSE.txt
Requires-Dist: importlib-metadata; python_version < "3.8"
Requires-Dist: cachetools==6.2.0
Requires-Dist: chardet==5.2.0
Requires-Dist: colorama==0.4.6
Requires-Dist: contourpy==1.3.3
Requires-Dist: cycler==0.12.1
Requires-Dist: distlib==0.4.0
Requires-Dist: filelock==3.19.1
Requires-Dist: fonttools==4.60.0
Requires-Dist: kiwisolver==1.4.9
Requires-Dist: matplotlib==3.10.6
Requires-Dist: numpy==2.3.3
Requires-Dist: packaging==25.0
Requires-Dist: pandas==2.3.2
Requires-Dist: pillow==11.3.0
Requires-Dist: platformdirs==4.4.0
Requires-Dist: pluggy==1.6.0
Requires-Dist: pyparsing==3.2.5
Requires-Dist: pyproject-api==1.9.1
Requires-Dist: python-dateutil==2.9.0.post0
Requires-Dist: pytz==2025.2
Requires-Dist: setuptools==80.9.0
Requires-Dist: setuptools-scm==9.2.0
Requires-Dist: six==1.17.0
Requires-Dist: tox==4.30.2
Requires-Dist: tzdata==2025.2
Requires-Dist: virtualenv==20.34.0
Requires-Dist: wheel==0.45.1
Provides-Extra: testing
Requires-Dist: setuptools; extra == "testing"
Requires-Dist: pytest; extra == "testing"
Requires-Dist: pytest-cov; extra == "testing"
Dynamic: license-file
